teax/__init__.py
teax/__init__.pyc
teax/__pkginfo__.py
teax/__pkginfo__.pyc
teax/config.py
teax/config.pyc
teax/interface.py
teax/messages.py
teax/messages.pyc
teax/terminal.py
teax/terminal.pyc
teax/engines/__init__.py
teax/engines/__init__.pyc
teax/engines/context.py
teax/engines/context.pyc
teax/engines/latex.py
teax/engines/latex.pyc
teax/engines/tex.py
teax/engines/tex.pyc
teax/engines/texinfo.py
teax/engines/texinfo.pyc
teax/plugins/__init__.py
teax/plugins/__init__.pyc
teax/plugins/bibtex.py
teax/plugins/bibtex.pyc
teax/plugins/makeglossaries.py
teax/plugins/makeglossaries.pyc
teax/plugins/makeindex.py
teax/plugins/makeindex.pyc
teax/system/__init__.py
teax/system/__init__.pyc
teax/system/core.py
teax/system/engine.py
teax/system/engine.pyc
teax/system/parser.py
teax/system/plugin.py
teax/system/plugin.pyc
teax/system/template.py
teax/templates/article-latex/document.tex
teax/utils/__init__.py
teax/utils/slugify.py
teax-0.0.dev1.dist-info/DESCRIPTION.rst
teax-0.0.dev1.dist-info/METADATA
teax-0.0.dev1.dist-info/RECORD
teax-0.0.dev1.dist-info/WHEEL
teax-0.0.dev1.dist-info/entry_points.txt
teax-0.0.dev1.dist-info/metadata.json
teax-0.0.dev1.dist-info/top_level.txt
