Metadata-Version: 2.0
Name: teax
Version: 0.0.dev1
Summary: Command line utilities for TeX.Arm yourself with secret powers!
Home-page: http://maciejczyzewski.me/teax
Author: Maciej A. Czyzewski
Author-email: mail@maciejczyzewski.me
License: BSD
Platform: any
Classifier: Environment :: Console
Classifier: Operating System :: OS Independent
Classifier: Intended Audience :: Science/Research
Classifier: Topic :: Utilities
Classifier: Topic :: Scientific/Engineering
Classifier: Topic :: Software Development :: Build Tools
Classifier: Topic :: Text Processing :: General
Classifier: Topic :: Text Processing :: Markup
Classifier: Topic :: Text Processing :: Markup :: LaTeX
Classifier: Programming Language :: Python
Classifier: Programming Language :: Python :: 2
Classifier: Programming Language :: Python :: 2.6
Classifier: Programming Language :: Python :: 3
Classifier: Programming Language :: Python :: 3.4
Classifier: Development Status :: 1 - Planning
Requires-Dist: click (>=2.0)
Requires-Dist: pep8 (>=1.7.0)
Requires-Dist: pytest (>=2.8.5)
Requires-Dist: tox (>=2.3.1)
Requires-Dist: watchdog (>=0.8.3)
